vvcm-1.0.0.dist-info/WHEEL
vvcm-1.0.0.dist-info/METADATA
vvcm-1.0.0.dist-info/RECORD
vvcm-1.0.0.dist-info/licenses/LICENSE
VVCM/py.typed
VVCM/VVCM_ext.pyi
VVCM/VVCM_ext.abi3.so
VVCM/__init__.py
include/eigen3/signature_of_eigen3_matrix_library
include/eigen3/unsupported/Eigen/SpecialFunctions
include/eigen3/unsupported/Eigen/NumericalDiff
include/eigen3/unsupported/Eigen/Polynomials
include/eigen3/unsupported/Eigen/AlignedVector3
include/eigen3/unsupported/Eigen/SparseExtra
include/eigen3/unsupported/Eigen/AutoDiff
include/eigen3/unsupported/Eigen/IterativeSolvers
include/eigen3/unsupported/Eigen/Skyline
include/eigen3/unsupported/Eigen/LevenbergMarquardt
include/eigen3/unsupported/Eigen/MatrixFunctions
include/eigen3/unsupported/Eigen/MPRealSupport
include/eigen3/unsupported/Eigen/Splines
include/eigen3/unsupported/Eigen/MoreVectorization
include/eigen3/unsupported/Eigen/KroneckerProduct
include/eigen3/unsupported/Eigen/AdolcForward
include/eigen3/unsupported/Eigen/ArpackSupport
include/eigen3/unsupported/Eigen/NonLinearOptimization
include/eigen3/unsupported/Eigen/BVH
include/eigen3/unsupported/Eigen/OpenGLSupport
include/eigen3/unsupported/Eigen/FFT
include/eigen3/unsupported/Eigen/EulerAngles
include/eigen3/unsupported/Eigen/CXX11/Tensor
include/eigen3/unsupported/Eigen/CXX11/ThreadPool
include/eigen3/unsupported/Eigen/CXX11/TensorSymmetry
include/eigen3/unsupported/Eigen/CXX11/src/Tensor/TensorUInt128.h
include/eigen3/unsupported/Eigen/CXX11/src/Tensor/TensorDeviceSycl.h
include/eigen3/unsupported/Eigen/CXX11/src/Tensor/TensorDeviceGpu.h
include/eigen3/unsupported/Eigen/CXX11/src/Tensor/TensorRef.h
include/eigen3/unsupported/Eigen/CXX11/src/Tensor/TensorReductionSycl.h
include/eigen3/unsupported/Eigen/CXX11/src/Tensor/TensorStorage.h
include/eigen3/unsupported/Eigen/CXX11/src/Tensor/TensorMeta.h
include/eigen3/unsupported/Eigen/CXX11/src/Tensor/TensorDimensionList.h
include/eigen3/unsupported/Eigen/CXX11/src/Tensor/TensorTraits.h
include/eigen3/unsupported/Eigen/CXX11/src/Tensor/TensorMap.h
