Metadata-Version: 2.1
Name: VVCM
Version: 1.0.0
Summary: Use VVCM and stable forward kinematics to predict object position for multi-robot transportation system with a deformable sheet.
Author-Email: MorningFrog <1098224028@qq.com>
Classifier: License :: OSI Approved :: Apache Software License
Classifier: Programming Language :: Python :: 3
Classifier: Operating System :: OS Independent
Project-URL: Homepage, https://github.com/MorningFrog/VVCM_cpp
Requires-Python: >=3.9
